py_text_scan.py
py_text_scan-0.1.0.dist-info/METADATA
py_text_scan-0.1.0.dist-info/WHEEL
py_text_scan-0.1.0.dist-info/top_level.txt
py_text_scan-0.1.0.dist-info/RECORD
