Metadata-Version: 2.4
Name: py_text_scan
Version: 0.1.0
Summary: A UNKNOWN py_text_scan
Home-page: https://github.com/Sidvilas/py_text_scan_package
Author: Sidvilas
Author-email: sdevilgv@gmail.com
Classifier: Programming Language :: Python :: 3
Classifier: Operating System :: OS Independent
Dynamic: author
Dynamic: author-email
Dynamic: classifier
Dynamic: home-page
Dynamic: summary
